barbthroat/__init__.py
barbthroat/chandler.py
barbthroat/connectors/__init__.py
barbthroat/connectors/binance.py
barbthroat/connectors/binance_paper_trade.py
barbthroat/custodians/__init__.py
barbthroat/custodians/savings.py
barbthroat/custodians/spot.py
barbthroat/http.py
barbthroat/hummingbot.py
barbthroat/indicators/__init__.py
barbthroat/indicators/changed_filter.py
barbthroat/indicators/four_week_rule.py
barbthroat/indicators/simple_moving_average.py
barbthroat/itertools.py
barbthroat/math.py
barbthroat/models.py
barbthroat/storages/__init__.py
barbthroat/storages/memory.py
barbthroat/storages/sqlite.py
barbthroat/tenacity.py
barbthroat/time.py
barbthroat-0.1.2.dist-info/METADATA
barbthroat-0.1.2.dist-info/WHEEL
barbthroat-0.1.2.dist-info/LICENSE
barbthroat-0.1.2.dist-info/RECORD
