Metadata-Version: 2.1
Name: barbthroat
Version: 0.1.2
Summary: A library to help write directional strategies for Hummingbot.
License: MIT
Author: discosultan
Author-email: jaanusvarus@gmail.com
Requires-Python: >=3.8,<4.0
Classifier: License :: OSI Approved :: MIT License
Classifier: Programming Language :: Python :: 3
Classifier: Programming Language :: Python :: 3.8
Classifier: Programming Language :: Python :: 3.9
Classifier: Programming Language :: Python :: 3.10
Classifier: Programming Language :: Python :: 3.11
Requires-Dist: aiohttp (>=3.8.3,<4.0.0)
Requires-Dist: aiolimiter (>=1.0.0,<2.0.0)
Requires-Dist: asyncstdlib (>=3.10.5,<4.0.0)
Requires-Dist: simplejson (>=3.18.0,<4.0.0)
Requires-Dist: tenacity (>=8.1.0,<9.0.0)
